<?xml version="1.0" encoding="utf-8"?>
<Definitions xmlns:xsi="http://www.w3.org/2001/XMLSchema-instance" xmlns:xsd="http://www.w3.org/2001/XMLSchema">
<Id>
<TypeId>LCDTextureDefinition</TypeId>
<SubtypeId>Offline</SubtypeId>
</Id>
<Id>
<TypeId>LCDTextureDefinition</TypeId>
<SubtypeId>Offline_wide</SubtypeId>
</Id>
<Id>
<TypeId>LCDTextureDefinition</TypeId>
<SubtypeId>Online</SubtypeId>
</Id>
<Id>
<TypeId>LCDTextureDefinition</TypeId>
<SubtypeId>Online_wide</SubtypeId>
</Id>
<Id>
<TypeId>LCDTextureDefinition</TypeId>
<SubtypeId>Arrow</SubtypeId>
</Id>
<Id>
<TypeId>LCDTextureDefinition</TypeId>
<SubtypeId>Cross</SubtypeId>
</Id>
<Id>
<TypeId>LCDTextureDefinition</TypeId>
<SubtypeId>Danger</SubtypeId>
</Id>
<Id>
<TypeId>LCDTextureDefinition</TypeId>
<SubtypeId>No Entry</SubtypeId>
</Id>
<Id>
<TypeId>LCDTextureDefinition</TypeId>
<SubtypeId>Construction</SubtypeId>
</Id>
<Id>
<TypeId>LCDTextureDefinition</TypeId>
<SubtypeId>White screen</SubtypeId>
</Id>
<Id>
<TypeId>LCDTextureDefinition</TypeId>
<SubtypeId>Grid</SubtypeId>
</Id>
<Id Type="LCDTextureDefinition" Subtype="DecorativeBracketLeft" />
<Id Type="LCDTextureDefinition" Subtype="DecorativeBracketRight" />
<Id Type="LCDTextureDefinition" Subtype="SquareTapered" />
<Id Type="LCDTextureDefinition" Subtype="SquareSimple" />
<Id Type="LCDTextureDefinition" Subtype="IconEnergy" />
<Id Type="LCDTextureDefinition" Subtype="IconHydrogen" />
<Id Type="LCDTextureDefinition" Subtype="IconOxygen" />
<Id Type="LCDTextureDefinition" Subtype="IconTemperature" />
<Id Type="LCDTextureDefinition" Subtype="AH_GravityHudNegativeDegrees" />
<Id Type="LCDTextureDefinition" Subtype="AH_GravityHudPositiveDegrees" />
<Id Type="LCDTextureDefinition" Subtype="AH_TextBox" />
<Id Type="LCDTextureDefinition" Subtype="AH_PullUp" />
<Id Type="LCDTextureDefinition" Subtype="AH_VelocityVector" />
<Id Type="LCDTextureDefinition" Subtype="AH_BoreSight" />
<Id Type="LCDTextureDefinition" Subtype="RightTriangle" />
<Id Type="LCDTextureDefinition" Subtype="Triangle" />
<Id Type="LCDTextureDefinition" Subtype="Circle" />
<Id Type="LCDTextureDefinition" Subtype="SemiCircle" />
<Id Type="LCDTextureDefinition" Subtype="CircleHollow" />
<Id Type="LCDTextureDefinition" Subtype="SquareHollow" />
<Id Type="LCDTextureDefinition" Subtype="UVChecker" />
<Public>false</Public>
<Id Type="LCDTextureDefinition" Subtype="OutOfOrder" />
<Public>false</Public>
</Definitions>
 
